nonebot_plugin_onebot_monitor/__init__.py
nonebot_plugin_onebot_monitor/config.py
nonebot_plugin_onebot_monitor/notice.py
nonebot_plugin_onebot_monitor/request.py
nonebot_plugin_onebot_monitor/utils.py
nonebot_plugin_qq_monitor-0.2.0.post1.dist-info/WHEEL
nonebot_plugin_qq_monitor-0.2.0.post1.dist-info/METADATA
nonebot_plugin_qq_monitor-0.2.0.post1.dist-info/RECORD
